ble2lsl/__init__.py
ble2lsl/ble2lsl.py
ble2lsl/utils.py
ble2lsl/devices/__init__.py
ble2lsl/devices/device.py
ble2lsl/devices/muse2016.py
ble2lsl/devices/ganglion/__init__.py
ble2lsl/devices/ganglion/ganglion.py
ble2lsl-0.1.3.dist-info/METADATA
ble2lsl-0.1.3.dist-info/RECORD
ble2lsl-0.1.3.dist-info/WHEEL
ble2lsl-0.1.3.dist-info/top_level.txt
