Metadata-Version: 2.1
Name: ble2lsl
Version: 0.1.3
Summary: Streaming data from Bluetooth Low Energy (BLE) devices through the Lab Streaming Layer (LSL).
Home-page: https://github.com/merlin-neurotech/ble2lsl
Author: Merlin Neurotech
Author-email: mnc@clubs.queensu.ca
License: BSD 3-Clause License
Platform: UNKNOWN
Classifier: License :: OSI Approved :: BSD License
Classifier: Programming Language :: Python
Classifier: Programming Language :: Python :: 3
Classifier: Programming Language :: Python :: 3.6
Classifier: Programming Language :: Python :: Implementation :: CPython
Classifier: Topic :: Scientific/Engineering
Classifier: Topic :: System :: Networking
Requires-Python: >=3.6.0
Requires-Dist: numpy (>=1.13.0)
Requires-Dist: pygatt (==3.2.0)
Requires-Dist: pylsl (>=1.10.5)
Requires-Dist: bitstring (>=3.1.5)
